longppl/__init__.py
longppl/longppl.py
longppl-0.3.0.dist-info/LICENSE
longppl-0.3.0.dist-info/METADATA
longppl-0.3.0.dist-info/WHEEL
longppl-0.3.0.dist-info/top_level.txt
longppl-0.3.0.dist-info/RECORD
