Metadata-Version: 2.1
Name: longppl
Version: 0.3.0
Summary: Calculate the longppl of long-context LLMs
Home-page: https://github.com/PKU-ML/LongPPL
Author: lzfang
Author-email: lzfang@stu.pku.edu.cn
Classifier: Programming Language :: Python :: 3
Classifier: License :: OSI Approved :: MIT License
Classifier: Operating System :: OS Independent
Requires-Python: >=3.7
License-File: LICENSE
Requires-Dist: transformers>=4.44.0
Requires-Dist: numpy
Requires-Dist: torch
Requires-Dist: datasets
